<?xml version="1.0" encoding="UTF-8"?><font-metrics metrics-version="2" type="TYPE0"><font-name>LiberationSans-BoldItalic</font-name><full-name>Liberation Sans Bold Italic</full-name><family-name>Liberation Sans</family-name><embed/><cap-height>687</cap-height><x-height>528</x-height><ascender>728</ascender><descender>-210</descender><bbox><left>-208</left><bottom>-303</bottom><right>1128</right><top>1029</top></bbox><flags>97</flags><stemv>0</stemv><italicangle>-12</italicangle><subtype>TYPE0</subtype><multibyte-extras><cid-type>CIDFontType2</cid-type><default-width>0</default-width><bfranges><bf gi="3" ue="126" us="32"/><bf gi="3" ue="160" us="160"/><bf gi="98" ue="172" us="161"/><bf gi="16" ue="173" us="173"/><bf gi="110" ue="383" us="174"/><bf gi="320" ue="402" us="402"/><bf gi="321" ue="511" us="506"/><bf gi="327" ue="539" us="536"/><bf gi="331" ue="711" us="710"/><bf gi="333" ue="713" us="713"/><bf gi="334" ue="733" us="728"/><bf gi="30" ue="894" us="894"/><bf gi="340" ue="906" us="900"/><bf gi="347" ue="908" us="908"/><bf gi="348" ue="929" us="910"/><bf gi="368" ue="974" us="931"/><bf gi="412" ue="1119" us="1024"/><bf gi="508" ue="1139" us="1138"/><bf gi="510" ue="1169" us="1168"/><bf gi="512" ue="7813" us="7808"/><bf gi="518" ue="7923" us="7922"/><bf gi="520" ue="8209" us="8208"/><bf gi="522" ue="8213" us="8211"/><bf gi="525" ue="8222" us="8215"/><bf gi="533" ue="8226" us="8224"/><bf gi="536" ue="8230" us="8230"/><bf gi="537" ue="8240" us="8240"/><bf gi="538" ue="8243" us="8242"/><bf gi="540" ue="8250" us="8249"/><bf gi="542" ue="8252" us="8252"/><bf gi="543" ue="8254" us="8254"/><bf gi="544" ue="8260" us="8260"/><bf gi="545" ue="8319" us="8319"/><bf gi="546" ue="8356" us="8355"/><bf gi="548" ue="8359" us="8359"/><bf gi="549" ue="8364" us="8364"/><bf gi="550" ue="8453" us="8453"/><bf gi="551" ue="8467" us="8467"/><bf gi="552" ue="8470" us="8470"/><bf gi="553" ue="8482" us="8482"/><bf gi="554" ue="8486" us="8486"/><bf gi="555" ue="8494" us="8494"/><bf gi="556" ue="8542" us="8539"/><bf gi="560" ue="8597" us="8592"/><bf gi="566" ue="8616" us="8616"/><bf gi="567" ue="8706" us="8706"/><bf gi="568" ue="8710" us="8710"/><bf gi="569" ue="8719" us="8719"/><bf gi="570" ue="8722" us="8721"/><bf gi="544" ue="8725" us="8725"/><bf gi="119" ue="8729" us="8729"/><bf gi="572" ue="8730" us="8730"/><bf gi="573" ue="8735" us="8734"/><bf gi="575" ue="8745" us="8745"/><bf gi="576" ue="8747" us="8747"/><bf gi="577" ue="8776" us="8776"/><bf gi="578" ue="8801" us="8800"/><bf gi="580" ue="8805" us="8804"/><bf gi="582" ue="8962" us="8962"/><bf gi="583" ue="8976" us="8976"/><bf gi="584" ue="8993" us="8992"/><bf gi="586" ue="9472" us="9472"/><bf gi="587" ue="9474" us="9474"/><bf gi="588" ue="9484" us="9484"/><bf gi="589" ue="9488" us="9488"/><bf gi="590" ue="9492" us="9492"/><bf gi="591" ue="9496" us="9496"/><bf gi="592" ue="9500" us="9500"/><bf gi="593" ue="9508" us="9508"/><bf gi="594" ue="9516" us="9516"/><bf gi="595" ue="9524" us="9524"/><bf gi="596" ue="9532" us="9532"/><bf gi="597" ue="9580" us="9552"/><bf gi="626" ue="9600" us="9600"/><bf gi="627" ue="9604" us="9604"/><bf gi="628" ue="9608" us="9608"/><bf gi="629" ue="9612" us="9612"/><bf gi="630" ue="9619" us="9616"/><bf gi="634" ue="9633" us="9632"/><bf gi="636" ue="9644" us="9642"/><bf gi="639" ue="9650" us="9650"/><bf gi="640" ue="9658" us="9658"/><bf gi="641" ue="9660" us="9660"/><bf gi="642" ue="9668" us="9668"/><bf gi="643" ue="9675" us="9674"/><bf gi="645" ue="9679" us="9679"/><bf gi="646" ue="9689" us="9688"/><bf gi="648" ue="9702" us="9702"/><bf gi="649" ue="9788" us="9786"/><bf gi="652" ue="9792" us="9792"/><bf gi="653" ue="9794" us="9794"/><bf gi="654" ue="9824" us="9824"/><bf gi="655" ue="9827" us="9827"/><bf gi="656" ue="9830" us="9829"/><bf gi="658" ue="9836" us="9834"/><bf gi="661" ue="61442" us="61441"/><bf gi="663" ue="61445" us="61445"/><bf gi="661" ue="64258" us="64257"/><bf gi="0" ue="65535" us="65535"/></bfranges><cid-widths start-index="0"><wx w="365" xMax="298" xMin="33" yMax="666" yMin="0"/><wx w="0" xMax="33" xMin="33" yMax="33" yMin="33"/><wx w="333" xMax="33" xMin="33" yMax="33" yMin="33"/><wx w="277" xMax="33" xMin="33" yMax="33" yMin="33"/><wx w="333" xMax="315" xMin="38" yMax="687" yMin="0"/><wx w="474" xMax="484" xMin="106" yMax="687" yMin="438"/><wx w="556" xMax="554" xMin="31" yMax="681" yMin="0"/><wx w="556" xMax="564" xMin="-5" yMax="742" yMin="-74"/><wx w="889" xMax="861" xMin="54" yMax="693" yMin="-7"/><wx w="722" xMax="657" xMin="23" yMax="691" yMin="-9"/><wx w="237" xMax="265" xMin="96" yMax="687" yMin="438"/><wx w="333" xMax="426" xMin="36" yMax="724" yMin="-207"/><wx w="333" xMax="303" xMin="-87" yMax="724" yMin="-207"/><wx w="389" xMax="428" xMin="42" yMax="687" yMin="315"/><wx w="583" xMax="562" xMin="61" yMax="586" yMin="78"/><wx w="277" xMax="192" xMin="-9" yMax="148" yMin="-154"/><wx w="333" xMax="304" xMin="27" yMax="318" yMin="199"/><wx w="277" xMax="192" xMin="22" yMax="148" yMin="0"/><wx w="277" xMax="365" xMin="-37" yMax="724" yMin="-20"/><wx w="556" xMax="546" xMin="41" yMax="698" yMin="-9"/><wx w="556" xMax="502" xMin="16" yMax="687" yMin="0"/><wx w="556" xMax="545" xMin="-15" yMax="698" yMin="0"/><wx w="556" xMax="544" xMin="7" yMax="698" yMin="-9"/><wx w="556" xMax="539" xMin="-16" yMax="687" yMin="0"/><wx w="556" xMax="567" xMin="9" yMax="687" yMin="-9"/><wx w="556" xMax="561" xMin="46" yMax="698" yMin="-9"/><wx w="556" xMax="595" xMin="69" yMax="687" yMin="0"/><wx w="556" xMax="554" xMin="13" yMax="697" yMin="-9"/><wx w="556" xMax="551" xMin="23" yMax="698" yMin="-9"/><wx w="333" xMax="282" xMin="43" yMax="504" yMin="0"/><wx w="333" xMax="282" xMin="11" yMax="504" yMin="-154"/><wx w="583" xMax="562" xMin="60" yMax="600" yMin="61"/><wx w="583" xMax="561" xMin="60" yMax="520" yMin="142"/><wx w="583" xMax="562" xMin="60" yMax="600" yMin="61"/><wx w="610" xMax="590" xMin="89" yMax="698" yMin="0"/><wx w="975" xMax="933" xMin="73" yMax="724" yMin="-143"/><wx w="722" xMax="649" xMin="-20" yMax="687" yMin="0"/><wx w="722" xMax="685" xMin="17" yMax="687" yMin="0"/><wx w="722" xMax="733" xMin="48" yMax="698" yMin="-9"/><wx w="722" xMax="693" xMin="17" yMax="687" yMin="0"/><wx w="666" xMax="691" xMin="17" yMax="687" yMin="0"/><wx w="610" xMax="632" xMin="17" yMax="687" yMin="0"/><wx w="777" xMax="747" xMin="48" yMax="698" yMin="-9"/><wx w="722" xMax="739" xMin="17" yMax="687" yMin="0"/><wx w="277" xMax="294" xMin="17" yMax="687" yMin="0"/><wx w="556" xMax="573" xMin="12" yMax="687" yMin="-9"/><wx w="722" xMax="782" xMin="17" yMax="687" yMin="0"/><wx w="610" xMax="552" xMin="17" yMax="687" yMin="0"/><wx w="833" xMax="850" xMin="17" yMax="687" yMin="0"/><wx w="722" xMax="739" xMin="17" yMax="687" yMin="0"/><wx w="777" xMax="761" xMin="48" yMax="698" yMin="-9"/><wx w="666" xMax="668" xMin="17" yMax="687" yMin="0"/><wx w="777" xMax="761" xMin="48" yMax="698" yMin="-195"/><wx w="722" xMax="715" xMin="17" yMax="687" yMin="0"/><wx w="666" xMax="656" xMin="12" yMax="698" yMin="-9"/><wx w="610" xMax="681" xMin="70" yMax="687" yMin="0"/><wx w="722" xMax="742" xMin="58" yMax="687" yMin="-9"/><wx w="666" xMax="736" xMin="83" yMax="687" yMin="0"/><wx w="943" xMax="1015" xMin="73" yMax="687" yMin="0"/><wx w="666" xMax="716" xMin="-45" yMax="687" yMin="0"/><wx w="666" xMax="742" xMin="83" yMax="687" yMin="0"/><wx w="610" xMax="642" xMin="-23" yMax="687" yMin="0"/><wx w="333" xMax="418" xMin="-26" yMax="724" yMin="-207"/><wx w="277" xMax="259" xMin="54" yMax="725" yMin="-20"/><wx w="333" xMax="360" xMin="-84" yMax="724" yMin="-207"/><wx w="583" xMax="581" xMin="41" yMax="687" yMin="250"/><wx w="556" xMax="516" xMin="-58" yMax="-83" yMin="-122"/><wx w="333" xMax="366" xMin="141" yMax="733" yMin="577"/><wx w="556" xMax="526" xMin="4" yMax="538" yMin="-9"/><wx w="610" xMax="582" xMin="17" yMax="724" yMin="-9"/><wx w="556" xMax="541" xMin="30" yMax="538" yMin="-9"/><wx w="610" xMax="627" xMin="28" yMax="724" yMin="-10"/><wx w="556" xMax="528" xMin="30" yMax="538" yMin="-9"/><wx w="333" xMax="416" xMin="36" yMax="724" yMin="0"/><wx w="610" xMax="593" xMin="-3" yMax="537" yMin="-207"/><wx w="610" xMax="568" xMin="17" yMax="724" yMin="0"/><wx w="277" xMax="294" xMin="17" yMax="724" yMin="0"/><wx w="277" xMax="294" xMin="-107" yMax="724" yMin="-207"/><wx w="556" xMax="597" xMin="17" yMax="724" yMin="0"/><wx w="277" xMax="294" xMin="17" yMax="724" yMin="0"/><wx w="889" xMax="847" xMin="17" yMax="537" yMin="0"/><wx w="610" xMax="568" xMin="17" yMax="537" yMin="0"/><wx w="610" xMax="578" xMin="30" yMax="537" yMin="-9"/><wx w="610" xMax="578" xMin="-21" yMax="538" yMin="-207"/><wx w="610" xMax="593" xMin="28" yMax="538" yMin="-207"/><wx w="389" xMax="434" xMin="17" yMax="538" yMin="0"/><wx w="556" xMax="521" xMin="11" yMax="536" yMin="-9"/><wx w="333" xMax="367" xMin="41" yMax="652" yMin="-7"/><wx w="610" xMax="593" xMin="41" yMax="528" yMin="-9"/><wx w="556" xMax="601" xMin="53" yMax="528" yMin="0"/><wx w="777" xMax="831" xMin="48" yMax="528" yMin="0"/><wx w="556" xMax="589" xMin="-43" yMax="528" yMin="0"/><wx w="556" xMax="597" xMin="-41" yMax="528" yMin="-207"/><wx w="500" xMax="500" xMin="-17" yMax="528" yMin="0"/><wx w="389" xMax="459" xMin="9" yMax="724" yMin="-207"/><wx w="279" xMax="221" xMin="93" yMax="724" yMin="-207"/><wx w="389" xMax="375" xMin="-75" yMax="725" yMin="-207"/><wx w="583" xMax="564" xMin="57" yMax="410" yMin="251"/><wx w="333" xMax="287" xMin="9" yMax="528" yMin="-159"/><wx w="556" xMax="547" xMin="37" yMax="687" yMin="-15"/><wx w="556" xMax="573" xMin="-24" yMax="698" yMin="0"/><wx w="556" xMax="535" xMin="35" yMax="583" yMin="83"/><wx w="556" xMax="635" xMin="19" yMax="687" yMin="0"/><wx w="279" xMax="221" xMin="93" yMax="724" yMin="-207"/><wx w="556" xMax="560" xMin="-20" yMax="696" yMin="-111"/><wx w="333" xMax="404" xMin="65" yMax="692" yMin="585"/><wx w="736" xMax="736" xMin="30" yMax="698" yMin="-7"/><wx w="370" xMax="390" xMin="50" yMax="692" yMin="336"/><wx w="556" xMax="540" xMin="35" yMax="458" yMin="67"/><wx w="583" xMax="538" xMin="36" yMax="387" yMin="68"/><wx w="736" xMax="736" xMin="30" yMax="698" yMin="-7"/><wx w="552" xMax="560" xMin="-8" yMax="754" yMin="708"/><wx w="399" xMax="405" xMin="92" yMax="695" yMin="388"/><wx w="548" xMax="543" xMin="42" yMax="620" yMin="0"/><wx w="333" xMax="354" xMin="34" yMax="696" yMin="339"/><wx w="333" xMax="354" xMin="46" yMax="696" yMin="335"/><wx w="333" xMax="383" xMin="124" yMax="733" yMin="577"/><wx w="576" xMax="556" xMin="-22" yMax="528" yMin="-207"/><wx w="556" xMax="540" xMin="51" yMax="687" yMin="-128"/><wx w="277" xMax="230" xMin="61" yMax="408" yMin="259"/><wx w="333" xMax="263" xMin="42" yMax="0" yMin="-207"/><wx w="333" xMax="320" xMin="47" yMax="689" yMin="338"/><wx w="365" xMax="404" xMin="49" yMax="692" yMin="336"/><wx w="556" xMax="523" xMin="18" yMax="458" yMin="67"/><wx w="833" xMax="757" xMin="47" yMax="689" yMin="0"/><wx w="833" xMax="783" xMin="47" yMax="689" yMin="0"/><wx w="833" xMax="757" xMin="53" yMax="696" yMin="0"/><wx w="610" xMax="513" xMin="12" yMax="528" yMin="-169"/><wx w="722" xMax="649" xMin="-20" yMax="882" yMin="0"/><wx w="722" xMax="649" xMin="-20" yMax="882" yMin="0"/><wx w="722" xMax="649" xMin="-20" yMax="895" yMin="0"/><wx w="722" xMax="657" xMin="-20" yMax="890" yMin="0"/><wx w="722" xMax="649" xMin="-20" yMax="854" yMin="0"/><wx w="722" xMax="649" xMin="-20" yMax="875" yMin="0"/><wx w="1000" xMax="1024" xMin="-47" yMax="687" yMin="0"/><wx w="722" xMax="724" xMin="39" yMax="698" yMin="-207"/><wx w="666" xMax="691" xMin="17" yMax="882" yMin="0"/><wx w="666" xMax="691" xMin="17" yMax="882" yMin="0"/><wx w="666" xMax="691" xMin="17" yMax="895" yMin="0"/><wx w="666" xMax="691" xMin="17" yMax="854" yMin="0"/><wx w="277" xMax="306" xMin="17" yMax="882" yMin="0"/><wx w="277" xMax="424" xMin="17" yMax="882" yMin="0"/><wx w="277" xMax="413" xMin="17" yMax="895" yMin="0"/><wx w="277" xMax="412" xMin="17" yMax="854" yMin="0"/><wx w="722" xMax="693" xMin="11" yMax="687" yMin="0"/><wx w="722" xMax="739" xMin="17" yMax="890" yMin="0"/><wx w="777" xMax="761" xMin="48" yMax="882" yMin="-9"/><wx w="777" xMax="761" xMin="48" yMax="882" yMin="-9"/><wx w="777" xMax="761" xMin="48" yMax="895" yMin="-9"/><wx w="777" xMax="761" xMin="48" yMax="890" yMin="-9"/><wx w="777" xMax="761" xMin="48" yMax="854" yMin="-9"/><wx w="583" xMax="561" xMin="61" yMax="583" yMin="82"/><wx w="777" xMax="809" xMin="17" yMax="715" yMin="-25"/><wx w="722" xMax="742" xMin="58" yMax="882" yMin="-9"/><wx w="722" xMax="742" xMin="58" yMax="882" yMin="-9"/><wx w="722" xMax="742" xMin="58" yMax="895" yMin="-9"/><wx w="722" xMax="742" xMin="58" yMax="854" yMin="-9"/><wx w="666" xMax="742" xMin="83" yMax="882" yMin="0"/><wx w="666" xMax="647" xMin="17" yMax="687" yMin="0"/><wx w="610" xMax="579" xMin="17" yMax="724" yMin="-9"/><wx w="556" xMax="526" xMin="4" yMax="733" yMin="-9"/><wx w="556" xMax="526" xMin="4" yMax="733" yMin="-9"/><wx w="556" xMax="526" xMin="4" yMax="746" yMin="-9"/><wx w="556" xMax="541" xMin="4" yMax="720" yMin="-9"/><wx w="556" xMax="526" xMin="4" yMax="692" yMin="-9"/><wx w="556" xMax="526" xMin="4" yMax="822" yMin="-9"/><wx w="889" xMax="854" xMin="20" yMax="538" yMin="-9"/><wx w="556" xMax="541" xMin="30" yMax="538" yMin="-207"/><wx w="556" xMax="528" xMin="30" yMax="733" yMin="-9"/><wx w="556" xMax="528" xMin="30" yMax="733" yMin="-9"/><wx w="556" xMax="528" xMin="30" yMax="746" yMin="-9"/><wx w="556" xMax="528" xMin="30" yMax="692" yMin="-9"/><wx w="277" xMax="272" xMin="17" yMax="733" yMin="0"/><wx w="277" xMax="384" xMin="17" yMax="733" yMin="0"/><wx w="277" xMax="375" xMin="13" yMax="746" yMin="0"/><wx w="277" xMax="377" xMin="17" yMax="692" yMin="0"/><wx w="610" xMax="572" xMin="28" yMax="731" yMin="-9"/><wx w="610" xMax="585" xMin="17" yMax="720" yMin="0"/><wx w="610" xMax="578" xMin="30" yMax="733" yMin="-9"/><wx w="610" xMax="578" xMin="30" yMax="733" yMin="-9"/><wx w="610" xMax="578" xMin="30" yMax="746" yMin="-9"/><wx w="610" xMax="578" xMin="30" yMax="720" yMin="-9"/><wx w="610" xMax="578" xMin="30" yMax="692" yMin="-9"/><wx w="548" xMax="535" xMin="33" yMax="583" yMin="83"/><wx w="610" xMax="598" xMin="20" yMax="544" yMin="-18"/><wx w="610" xMax="593" xMin="41" yMax="733" yMin="-9"/><wx w="610" xMax="593" xMin="41" yMax="733" yMin="-9"/><wx w="610" xMax="593" xMin="41" yMax="746" yMin="-9"/><wx w="610" xMax="593" xMin="41" yMax="692" yMin="-9"/><wx w="556" xMax="597" xMin="-41" yMax="733" yMin="-207"/><wx w="610" xMax="578" xMin="-22" yMax="724" yMin="-207"/><wx w="556" xMax="606" xMin="-32" yMax="690" yMin="-207"/><wx w="722" xMax="649" xMin="-20" yMax="832" yMin="0"/><wx w="556" xMax="526" xMin="4" yMax="669" yMin="-9"/><wx w="722" xMax="649" xMin="-20" yMax="890" yMin="0"/><wx w="556" xMax="538" xMin="4" yMax="735" yMin="-9"/><wx w="722" xMax="649" xMin="-20" yMax="687" yMin="-202"/><wx w="556" xMax="526" xMin="4" yMax="538" yMin="-207"/><wx w="722" xMax="733" xMin="48" yMax="882" yMin="-9"/><wx w="556" xMax="553" xMin="30" yMax="733" yMin="-9"/><wx w="722" xMax="733" xMin="48" yMax="895" yMin="-9"/><wx w="556" xMax="541" xMin="30" yMax="746" yMin="-9"/><wx w="722" xMax="733" xMin="48" yMax="853" yMin="-9"/><wx w="556" xMax="541" xMin="30" yMax="724" yMin="-9"/><wx w="722" xMax="733" xMin="48" yMax="895" yMin="-9"/><wx w="556" xMax="547" xMin="30" yMax="746" yMin="-9"/><wx w="722" xMax="693" xMin="17" yMax="895" yMin="0"/><wx w="739" xMax="811" xMin="28" yMax="724" yMin="-10"/><wx w="722" xMax="693" xMin="11" yMax="687" yMin="0"/><wx w="610" xMax="679" xMin="28" yMax="724" yMin="-10"/><wx w="666" xMax="691" xMin="17" yMax="832" yMin="0"/><wx w="556" xMax="528" xMin="30" yMax="669" yMin="-9"/><wx w="666" xMax="691" xMin="17" yMax="890" yMin="0"/><wx w="556" xMax="532" xMin="30" yMax="735" yMin="-9"/><wx w="666" xMax="691" xMin="17" yMax="856" yMin="0"/><wx w="556" xMax="528" xMin="30" yMax="724" yMin="-9"/><wx w="666" xMax="691" xMin="17" yMax="687" yMin="-207"/><wx w="556" xMax="528" xMin="30" yMax="538" yMin="-197"/><wx w="666" xMax="691" xMin="17" yMax="895" yMin="0"/><wx w="556" xMax="540" xMin="30" yMax="746" yMin="-9"/><wx w="777" xMax="747" xMin="48" yMax="895" yMin="-9"/><wx w="610" xMax="593" xMin="-3" yMax="746" yMin="-207"/><wx w="777" xMax="747" xMin="48" yMax="890" yMin="-9"/><wx w="610" xMax="593" xMin="-3" yMax="735" yMin="-207"/><wx w="777" xMax="747" xMin="48" yMax="856" yMin="-9"/><wx w="610" xMax="593" xMin="-3" yMax="724" yMin="-207"/><wx w="777" xMax="747" xMin="48" yMax="698" yMin="-222"/><wx w="610" xMax="593" xMin="-3" yMax="785" yMin="-207"/><wx w="722" xMax="739" xMin="17" yMax="895" yMin="0"/><wx w="610" xMax="584" xMin="17" yMax="934" yMin="0"/><wx w="722" xMax="780" xMin="17" yMax="687" yMin="0"/><wx w="610" xMax="564" xMin="17" yMax="724" yMin="0"/><wx w="277" xMax="441" xMin="17" yMax="889" yMin="0"/><wx w="277" xMax="400" xMin="-7" yMax="720" yMin="0"/><wx w="277" xMax="387" xMin="17" yMax="832" yMin="0"/><wx w="277" xMax="358" xMin="17" yMax="669" yMin="0"/><wx w="277" xMax="423" xMin="17" yMax="890" yMin="0"/><wx w="277" xMax="394" xMin="17" yMax="735" yMin="0"/><wx w="277" xMax="294" xMin="-11" yMax="687" yMin="-207"/><wx w="277" xMax="294" xMin="-18" yMax="724" yMin="-207"/><wx w="277" xMax="322" xMin="17" yMax="856" yMin="0"/><wx w="277" xMax="256" xMin="17" yMax="528" yMin="0"/><wx w="782" xMax="799" xMin="17" yMax="687" yMin="-9"/><wx w="556" xMax="572" xMin="17" yMax="724" yMin="-207"/><wx w="556" xMax="625" xMin="12" yMax="895" yMin="-9"/><wx w="277" xMax="368" xMin="-107" yMax="746" yMin="-207"/><wx w="722" xMax="782" xMin="17" yMax="687" yMin="-222"/><wx w="556" xMax="597" xMin="17" yMax="724" yMin="-222"/><wx w="556" xMax="597" xMin="17" yMax="528" yMin="0"/><wx w="610" xMax="552" xMin="17" yMax="882" yMin="0"/><wx w="277" xMax="425" xMin="17" yMax="921" yMin="0"/><wx w="610" xMax="552" xMin="17" yMax="687" yMin="-222"/><wx w="277" xMax="294" xMin="-7" yMax="724" yMin="-222"/><wx w="610" xMax="555" xMin="17" yMax="687" yMin="0"/><wx w="395" xMax="478" xMin="17" yMax="724" yMin="0"/><wx w="610" xMax="552" xMin="17" yMax="687" yMin="0"/><wx w="479" xMax="458" xMin="17" yMax="724" yMin="0"/><wx w="610" xMax="552" xMin="-9" yMax="687" yMin="0"/><wx w="277" xMax="312" xMin="2" yMax="724" yMin="0"/><wx w="722" xMax="739" xMin="17" yMax="882" yMin="0"/><wx w="610" xMax="568" xMin="17" yMax="733" yMin="0"/><wx w="722" xMax="739" xMin="17" yMax="687" yMin="-222"/><wx w="610" xMax="568" xMin="17" yMax="537" yMin="-222"/><wx w="722" xMax="739" xMin="17" yMax="895" yMin="0"/><wx w="610" xMax="568" xMin="17" yMax="746" yMin="0"/><wx w="708" xMax="666" xMin="3" yMax="687" yMin="0"/><wx w="723" xMax="710" xMin="17" yMax="697" yMin="-9"/><wx w="610" xMax="568" xMin="17" yMax="537" yMin="-207"/><wx w="777" xMax="761" xMin="48" yMax="832" yMin="-9"/><wx w="610" xMax="578" xMin="30" yMax="669" yMin="-9"/><wx w="777" xMax="761" xMin="48" yMax="890" yMin="-9"/><wx w="610" xMax="578" xMin="30" yMax="735" yMin="-9"/><wx w="777" xMax="761" xMin="48" yMax="883" yMin="-9"/><wx w="610" xMax="636" xMin="30" yMax="733" yMin="-9"/><wx w="1000" xMax="1024" xMin="50" yMax="693" yMin="-4"/><wx w="943" xMax="921" xMin="28" yMax="538" yMin="-9"/><wx w="722" xMax="715" xMin="17" yMax="882" yMin="0"/><wx w="389" xMax="472" xMin="17" yMax="733" yMin="0"/><wx w="722" xMax="715" xMin="17" yMax="687" yMin="-222"/><wx w="389" xMax="434" xMin="-8" yMax="538" yMin="-222"/><wx w="722" xMax="715" xMin="17" yMax="895" yMin="0"/><wx w="389" xMax="483" xMin="17" yMax="746" yMin="0"/><wx w="666" xMax="656" xMin="12" yMax="882" yMin="-9"/><wx w="556" xMax="523" xMin="11" yMax="733" yMin="-9"/><wx w="666" xMax="656" xMin="12" yMax="895" yMin="-9"/><wx w="556" xMax="521" xMin="11" yMax="746" yMin="-9"/><wx w="666" xMax="656" xMin="12" yMax="698" yMin="-207"/><wx w="556" xMax="521" xMin="11" yMax="536" yMin="-207"/><wx w="666" xMax="656" xMin="12" yMax="895" yMin="-9"/><wx w="556" xMax="533" xMin="11" yMax="746" yMin="-9"/><wx w="610" xMax="681" xMin="70" yMax="687" yMin="-207"/><wx w="333" xMax="367" xMin="36" yMax="652" yMin="-207"/><wx w="610" xMax="681" xMin="70" yMax="895" yMin="0"/><wx w="479" xMax="555" xMin="41" yMax="724" yMin="-7"/><wx w="610" xMax="681" xMin="70" yMax="687" yMin="0"/><wx w="333" xMax="367" xMin="12" yMax="652" yMin="-7"/><wx w="722" xMax="742" xMin="58" yMax="889" yMin="-9"/><wx w="610" xMax="593" xMin="41" yMax="720" yMin="-9"/><wx w="722" xMax="742" xMin="58" yMax="830" yMin="-9"/><wx w="610" xMax="593" xMin="41" yMax="669" yMin="-9"/><wx w="722" xMax="742" xMin="58" yMax="890" yMin="-9"/><wx w="610" xMax="593" xMin="41" yMax="735" yMin="-9"/><wx w="722" xMax="742" xMin="58" yMax="965" yMin="-9"/><wx w="610" xMax="593" xMin="41" yMax="802" yMin="-9"/><wx w="722" xMax="742" xMin="58" yMax="883" yMin="-9"/><wx w="610" xMax="654" xMin="41" yMax="733" yMin="-9"/><wx w="722" xMax="742" xMin="58" yMax="687" yMin="-207"/><wx w="610" xMax="593" xMin="41" yMax="528" yMin="-207"/><wx w="943" xMax="1015" xMin="73" yMax="895" yMin="0"/><wx w="777" xMax="831" xMin="48" yMax="746" yMin="0"/><wx w="666" xMax="742" xMin="83" yMax="895" yMin="0"/><wx w="556" xMax="597" xMin="-41" yMax="746" yMin="-207"/><wx w="666" xMax="728" xMin="69" yMax="854" yMin="0"/><wx w="610" xMax="642" xMin="-23" yMax="882" yMin="0"/><wx w="500" xMax="504" xMin="-17" yMax="733" yMin="0"/><wx w="610" xMax="642" xMin="-23" yMax="853" yMin="0"/><wx w="500" xMax="500" xMin="-17" yMax="724" yMin="0"/><wx w="610" xMax="642" xMin="-23" yMax="895" yMin="0"/><wx w="500" xMax="517" xMin="-17" yMax="746" yMin="0"/><wx w="277" xMax="397" xMin="17" yMax="724" yMin="0"/><wx w="556" xMax="527" xMin="106" yMax="724" yMin="-207"/><wx w="722" xMax="683" xMin="-20" yMax="1029" yMin="0"/><wx w="556" xMax="585" xMin="4" yMax="961" yMin="-9"/><wx w="1000" xMax="1024" xMin="-47" yMax="882" yMin="0"/><wx w="889" xMax="854" xMin="20" yMax="733" yMin="-9"/><wx w="777" xMax="809" xMin="17" yMax="882" yMin="-25"/><wx w="610" xMax="598" xMin="20" yMax="733" yMin="-18"/><wx w="666" xMax="656" xMin="12" yMax="698" yMin="-222"/><wx w="556" xMax="521" xMin="11" yMax="536" yMin="-222"/><wx w="610" xMax="681" xMin="70" yMax="687" yMin="-222"/><wx w="333" xMax="367" xMin="41" yMax="652" yMin="-222"/><wx w="333" xMax="399" xMin="37" yMax="746" yMin="577"/><wx w="333" xMax="434" xMin="71" yMax="746" yMin="577"/><wx w="333" xMax="385" xMin="81" yMax="669" yMin="587"/><wx w="333" xMax="423" xMin="76" yMax="735" yMin="577"/><wx w="333" xMax="318" xMin="161" yMax="724" yMin="623"/><wx w="333" xMax="358" xMin="110" yMax="802" yMin="554"/><wx w="333" xMax="236" xMin="51" yMax="4" yMin="-207"/><wx w="333" xMax="441" xMin="33" yMax="720" yMin="577"/><wx w="333" xMax="483" xMin="28" yMax="733" yMin="577"/><wx w="333" xMax="264" xMin="74" yMax="736" yMin="577"/><wx w="333" xMax="350" xMin="-28" yMax="791" yMin="581"/><wx w="722" xMax="649" xMin="-20" yMax="688" yMin="0"/><wx w="333" xMax="258" xMin="89" yMax="408" yMin="259"/><wx w="854" xMax="876" xMin="74" yMax="688" yMin="0"/><wx w="905" xMax="922" xMin="74" yMax="688" yMin="0"/><wx w="473" xMax="490" xMin="74" yMax="688" yMin="0"/><wx w="844" xMax="827" xMin="27" yMax="698" yMin="-9"/><wx w="930" xMax="1005" xMin="96" yMax="688" yMin="0"/><wx w="847" xMax="784" xMin="-39" yMax="698" yMin="0"/><wx w="277" xMax="395" xMin="17" yMax="791" yMin="0"/><wx w="722" xMax="649" xMin="-20" yMax="687" yMin="0"/><wx w="722" xMax="685" xMin="17" yMax="687" yMin="0"/><wx w="609" xMax="649" xMin="17" yMax="687" yMin="0"/><wx w="671" xMax="626" xMin="-31" yMax="687" yMin="0"/><wx w="666" xMax="691" xMin="17" yMax="687" yMin="0"/><wx w="610" xMax="642" xMin="-23" yMax="687" yMin="0"/><wx w="722" xMax="739" xMin="17" yMax="687" yMin="0"/><wx w="777" xMax="761" xMin="48" yMax="698" yMin="-9"/><wx w="277" xMax="294" xMin="17" yMax="687" yMin="0"/><wx w="722" xMax="782" xMin="17" yMax="687" yMin="0"/><wx w="666" xMax="607" xMin="-45" yMax="688" yMin="0"/><wx w="833" xMax="850" xMin="17" yMax="687" yMin="0"/><wx w="722" xMax="739" xMin="17" yMax="687" yMin="0"/><wx w="657" xMax="674" xMin="-3" yMax="687" yMin="0"/><wx w="777" xMax="761" xMin="48" yMax="698" yMin="-9"/><wx w="717" xMax="734" xMin="17" yMax="687" yMin="0"/><wx w="666" xMax="668" xMin="17" yMax="687" yMin="0"/><wx w="590" xMax="606" xMin="-22" yMax="687" yMin="0"/><wx w="610" xMax="681" xMin="70" yMax="687" yMin="0"/><wx w="666" xMax="742" xMin="83" yMax="687" yMin="0"/><wx w="822" xMax="807" xMin="46" yMax="692" yMin="-5"/><wx w="666" xMax="716" xMin="-45" yMax="687" yMin="0"/><wx w="828" xMax="865" xMin="83" yMax="687" yMin="0"/><wx w="780" xMax="759" xMin="-15" yMax="698" yMin="0"/><wx w="277" xMax="412" xMin="17" yMax="854" yMin="0"/><wx w="666" xMax="728" xMin="69" yMax="854" yMin="0"/><wx w="620" xMax="654" xMin="27" yMax="736" yMin="-10"/><wx w="478" xMax="487" xMin="12" yMax="736" yMin="-9"/><wx w="610" xMax="568" xMin="18" yMax="736" yMin="-207"/><wx w="277" xMax="333" xMin="32" yMax="736" yMin="0"/><wx w="591" xMax="548" xMin="49" yMax="791" yMin="-9"/><wx w="620" xMax="654" xMin="27" yMax="537" yMin="-10"/><wx w="620" xMax="587" xMin="-21" yMax="724" yMin="-207"/><wx w="556" xMax="601" xMin="52" yMax="528" yMin="-207"/><wx w="610" xMax="611" xMin="26" yMax="724" yMin="-9"/><wx w="478" xMax="487" xMin="12" yMax="537" yMin="-9"/><wx w="491" xMax="531" xMin="23" yMax="724" yMin="-196"/><wx w="610" xMax="568" xMin="18" yMax="537" yMin="-207"/><wx w="557" xMax="537" xMin="52" yMax="724" yMin="-9"/><wx w="277" xMax="256" xMin="32" yMax="528" yMin="0"/><wx w="565" xMax="602" xMin="18" yMax="528" yMin="0"/><wx w="556" xMax="491" xMin="-44" yMax="750" yMin="0"/><wx w="603" xMax="590" xMin="-22" yMax="528" yMin="-207"/><wx w="556" xMax="546" xMin="51" yMax="528" yMin="0"/><wx w="449" xMax="495" xMin="23" yMax="724" yMin="-195"/><wx w="610" xMax="578" xMin="30" yMax="537" yMin="-9"/><wx w="711" xMax="721" xMin="32" yMax="528" yMin="-9"/><wx w="605" xMax="574" xMin="-22" yMax="538" yMin="-207"/><wx w="532" xMax="529" xMin="37" yMax="538" yMin="-196"/><wx w="663" xMax="695" xMin="31" yMax="528" yMin="-9"/><wx w="408" xMax="451" xMin="27" yMax="528" yMin="-9"/><wx w="591" xMax="548" xMin="49" yMax="528" yMin="-9"/><wx w="703" xMax="673" xMin="31" yMax="540" yMin="-207"/><wx w="577" xMax="600" xMin="-87" yMax="539" yMin="-207"/><wx w="772" xMax="755" xMin="47" yMax="654" yMin="-207"/><wx w="834" xMax="800" xMin="26" yMax="538" yMin="-9"/><wx w="277" xMax="377" xMin="32" yMax="692" yMin="0"/><wx w="591" xMax="548" xMin="49" yMax="692" yMin="-9"/><wx w="610" xMax="578" xMin="30" yMax="736" yMin="-9"/><wx w="591" xMax="548" xMin="49" yMax="736" yMin="-9"/><wx w="834" xMax="800" xMin="26" yMax="736" yMin="-9"/><wx w="666" xMax="691" xMin="17" yMax="882" yMin="0"/><wx w="666" xMax="691" xMin="17" yMax="854" yMin="0"/><wx w="885" xMax="836" xMin="70" yMax="687" yMin="-9"/><wx w="613" xMax="650" xMin="17" yMax="882" yMin="0"/><wx w="718" xMax="733" xMin="48" yMax="698" yMin="-9"/><wx w="666" xMax="656" xMin="12" yMax="698" yMin="-9"/><wx w="277" xMax="294" xMin="17" yMax="687" yMin="0"/><wx w="277" xMax="412" xMin="17" yMax="854" yMin="0"/><wx w="556" xMax="573" xMin="12" yMax="687" yMin="-9"/><wx w="1094" xMax="1055" xMin="-60" yMax="687" yMin="-7"/><wx w="1041" xMax="1002" xMin="18" yMax="687" yMin="0"/><wx w="853" xMax="793" xMin="70" yMax="687" yMin="0"/><wx w="622" xMax="671" xMin="17" yMax="882" yMin="0"/><wx w="719" xMax="736" xMin="17" yMax="882" yMin="0"/><wx w="677" xMax="740" xMin="26" yMax="909" yMin="-9"/><wx w="719" xMax="735" xMin="17" yMax="687" yMin="-199"/><wx w="722" xMax="649" xMin="-20" yMax="687" yMin="0"/><wx w="708" xMax="668" xMin="17" yMax="687" yMin="0"/><wx w="722" xMax="685" xMin="17" yMax="687" yMin="0"/><wx w="613" xMax="650" xMin="17" yMax="687" yMin="0"/><wx w="722" xMax="696" xMin="-70" yMax="687" yMin="-199"/><wx w="666" xMax="691" xMin="17" yMax="687" yMin="0"/><wx w="927" xMax="971" xMin="-41" yMax="687" yMin="0"/><wx w="642" xMax="621" xMin="13" yMax="697" yMin="-9"/><wx w="719" xMax="736" xMin="17" yMax="687" yMin="0"/><wx w="719" xMax="736" xMin="17" yMax="909" yMin="0"/><wx w="614" xMax="671" xMin="17" yMax="687" yMin="0"/><wx w="687" xMax="704" xMin="-60" yMax="687" yMin="-7"/><wx w="833" xMax="850" xMin="17" yMax="687" yMin="0"/><wx w="722" xMax="739" xMin="17" yMax="687" yMin="0"/><wx w="777" xMax="761" xMin="48" yMax="698" yMin="-9"/><wx w="719" xMax="736" xMin="17" yMax="687" yMin="0"/><wx w="666" xMax="668" xMin="17" yMax="687" yMin="0"/><wx w="722" xMax="733" xMin="48" yMax="698" yMin="-9"/><wx w="610" xMax="681" xMin="70" yMax="687" yMin="0"/><wx w="677" xMax="740" xMin="26" yMax="687" yMin="-9"/><wx w="780" xMax="777" xMin="38" yMax="692" yMin="-5"/><wx w="666" xMax="716" xMin="-45" yMax="687" yMin="0"/><wx w="729" xMax="712" xMin="17" yMax="687" yMin="-199"/><wx w="708" xMax="725" xMin="86" yMax="687" yMin="0"/><wx w="979" xMax="996" xMin="17" yMax="687" yMin="0"/><wx w="988" xMax="972" xMin="17" yMax="687" yMin="-199"/><wx w="854" xMax="814" xMin="72" yMax="687" yMin="0"/><wx w="1000" xMax="1017" xMin="17" yMax="687" yMin="0"/><wx w="708" xMax="668" xMin="17" yMax="687" yMin="0"/><wx w="718" xMax="702" xMin="20" yMax="698" yMin="-9"/><wx w="1041" xMax="992" xMin="17" yMax="698" yMin="-9"/><wx w="729" xMax="746" xMin="-21" yMax="687" yMin="0"/><wx w="556" xMax="526" xMin="4" yMax="538" yMin="-9"/><wx w="619" xMax="641" xMin="45" yMax="733" yMin="-9"/><wx w="604" xMax="578" xMin="19" yMax="533" yMin="-9"/><wx w="533" xMax="502" xMin="14" yMax="538" yMin="-9"/><wx w="618" xMax="582" xMin="29" yMax="724" yMin="-9"/><wx w="556" xMax="528" xMin="30" yMax="538" yMin="-9"/><wx w="736" xMax="778" xMin="-44" yMax="528" yMin="0"/><wx w="510" xMax="489" xMin="5" yMax="538" yMin="-9"/><wx w="610" xMax="593" xMin="41" yMax="528" yMin="-9"/><wx w="610" xMax="593" xMin="41" yMax="748" yMin="-9"/><wx w="506" xMax="547" xMin="17" yMax="528" yMin="0"/><wx w="622" xMax="604" xMin="-40" yMax="528" yMin="-9"/><wx w="739" xMax="720" xMin="17" yMax="528" yMin="0"/><wx w="604" xMax="584" xMin="17" yMax="528" yMin="0"/><wx w="610" xMax="578" xMin="30" yMax="537" yMin="-9"/><wx w="610" xMax="568" xMin="17" yMax="537" yMin="0"/><wx w="610" xMax="578" xMin="-21" yMax="538" yMin="-207"/><wx w="556" xMax="541" xMin="30" yMax="538" yMin="-9"/><wx w="889" xMax="847" xMin="17" yMax="537" yMin="0"/><wx w="556" xMax="597" xMin="-41" yMax="528" yMin="-207"/><wx w="884" xMax="853" xMin="30" yMax="724" yMin="-207"/><wx w="556" xMax="589" xMin="-43" yMax="528" yMin="0"/><wx w="645" xMax="593" xMin="41" yMax="528" yMin="-199"/><wx w="583" xMax="562" xMin="51" yMax="528" yMin="0"/><wx w="889" xMax="872" xMin="41" yMax="528" yMin="-9"/><wx w="935" xMax="877" xMin="41" yMax="528" yMin="-199"/><wx w="707" xMax="648" xMin="37" yMax="528" yMin="-9"/><wx w="854" xMax="836" xMin="18" yMax="528" yMin="-9"/><wx w="593" xMax="535" xMin="18" yMax="528" yMin="-9"/><wx w="551" xMax="520" xMin="7" yMax="537" yMin="-9"/><wx w="864" xMax="832" xMin="17" yMax="539" yMin="-9"/><wx w="588" xMax="571" xMin="-45" yMax="528" yMin="0"/><wx w="556" xMax="528" xMin="30" yMax="738" yMin="-9"/><wx w="556" xMax="528" xMin="30" yMax="692" yMin="-9"/><wx w="610" xMax="564" xMin="17" yMax="724" yMin="-207"/><wx w="469" xMax="488" xMin="17" yMax="733" yMin="0"/><wx w="562" xMax="546" xMin="30" yMax="538" yMin="-9"/><wx w="556" xMax="521" xMin="11" yMax="536" yMin="-9"/><wx w="277" xMax="291" xMin="17" yMax="724" yMin="0"/><wx w="277" xMax="377" xMin="17" yMax="692" yMin="0"/><wx w="277" xMax="294" xMin="-107" yMax="724" yMin="-207"/><wx w="969" xMax="910" xMin="-40" yMax="528" yMin="-9"/><wx w="905" xMax="847" xMin="18" yMax="528" yMin="-9"/><wx w="610" xMax="564" xMin="17" yMax="724" yMin="0"/><wx w="506" xMax="547" xMin="17" yMax="733" yMin="0"/><wx w="619" xMax="593" xMin="41" yMax="733" yMin="-9"/><wx w="556" xMax="597" xMin="-41" yMax="748" yMin="-207"/><wx w="610" xMax="593" xMin="41" yMax="528" yMin="-199"/><wx w="777" xMax="761" xMin="48" yMax="698" yMin="-9"/><wx w="610" xMax="578" xMin="30" yMax="537" yMin="-9"/><wx w="575" xMax="646" xMin="17" yMax="888" yMin="0"/><wx w="466" xMax="512" xMin="17" yMax="727" yMin="0"/><wx w="943" xMax="1015" xMin="73" yMax="882" yMin="0"/><wx w="777" xMax="831" xMin="48" yMax="733" yMin="0"/><wx w="943" xMax="1015" xMin="73" yMax="882" yMin="0"/><wx w="777" xMax="831" xMin="48" yMax="733" yMin="0"/><wx w="943" xMax="1015" xMin="73" yMax="854" yMin="0"/><wx w="777" xMax="831" xMin="48" yMax="692" yMin="0"/><wx w="666" xMax="742" xMin="83" yMax="882" yMin="0"/><wx w="556" xMax="597" xMin="-41" yMax="733" yMin="-207"/><wx w="333" xMax="304" xMin="27" yMax="318" yMin="199"/><wx w="333" xMax="304" xMin="27" yMax="318" yMin="199"/><wx w="556" xMax="532" xMin="21" yMax="317" yMin="218"/><wx w="1000" xMax="1009" xMin="-9" yMax="317" yMin="218"/><wx w="1000" xMax="1009" xMin="-9" yMax="317" yMin="218"/><wx w="552" xMax="516" xMin="-58" yMax="-83" yMin="-250"/><wx w="277" xMax="289" xMin="92" yMax="687" yMin="405"/><wx w="277" xMax="289" xMin="92" yMax="687" yMin="405"/><wx w="277" xMax="188" xMin="-8" yMax="126" yMin="-154"/><wx w="277" xMax="291" xMin="124" yMax="687" yMin="405"/><wx w="500" xMax="499" xMin="92" yMax="687" yMin="405"/><wx w="500" xMax="499" xMin="92" yMax="687" yMin="405"/><wx w="500" xMax="401" xMin="-4" yMax="126" yMin="-154"/><wx w="556" xMax="545" xMin="104" yMax="724" yMin="-67"/><wx w="556" xMax="548" xMin="24" yMax="724" yMin="-68"/><wx w="350" xMax="330" xMin="43" yMax="473" yMin="186"/><wx w="1000" xMax="871" xMin="64" yMax="148" yMin="0"/><wx w="1000" xMax="965" xMin="35" yMax="692" yMin="-3"/><wx w="239" xMax="275" xMin="95" yMax="687" yMin="434"/><wx w="479" xMax="514" xMin="95" yMax="687" yMin="434"/><wx w="333" xMax="316" xMin="35" yMax="458" yMin="67"/><wx w="333" xMax="297" xMin="16" yMax="458" yMin="67"/><wx w="604" xMax="587" xMin="38" yMax="687" yMin="0"/><wx w="333" xMax="341" xMin="-8" yMax="791" yMin="709"/><wx w="166" xMax="418" xMin="-208" yMax="687" yMin="0"/><wx w="395" xMax="379" xMin="44" yMax="576" yMin="253"/><wx w="556" xMax="617" xMin="-20" yMax="687" yMin="0"/><wx w="556" xMax="573" xMin="-24" yMax="698" yMin="0"/><wx w="1104" xMax="1060" xMin="28" yMax="687" yMin="-9"/><wx w="556" xMax="592" xMin="13" yMax="698" yMin="-8"/><wx w="885" xMax="859" xMin="63" yMax="695" yMin="-7"/><wx w="516" xMax="520" xMin="17" yMax="697" yMin="-9"/><wx w="1145" xMax="1128" xMin="20" yMax="687" yMin="0"/><wx w="1000" xMax="906" xMin="90" yMax="687" yMin="375"/><wx w="768" xMax="730" xMin="45" yMax="698" yMin="0"/><wx w="600" xMax="565" xMin="47" yMax="535" yMin="-16"/><wx w="833" xMax="793" xMin="63" yMax="689" yMin="-3"/><wx w="833" xMax="793" xMin="73" yMax="696" yMin="-3"/><wx w="833" xMax="793" xMin="71" yMax="687" yMin="-3"/><wx w="833" xMax="767" xMin="86" yMax="687" yMin="-3"/><wx w="999" xMax="822" xMin="230" yMax="407" yMin="172"/><wx w="500" xMax="367" xMin="132" yMax="562" yMin="-29"/><wx w="1000" xMax="822" xMin="230" yMax="407" yMin="172"/><wx w="500" xMax="367" xMin="132" yMax="562" yMin="-29"/><wx w="999" xMax="822" xMin="230" yMax="407" yMin="172"/><wx w="500" xMax="367" xMin="132" yMax="562" yMin="-29"/><wx w="500" xMax="367" xMin="132" yMax="562" yMin="-89"/><wx w="494" xMax="466" xMin="30" yMax="716" yMin="-12"/><wx w="611" xMax="590" xMin="20" yMax="687" yMin="0"/><wx w="823" xMax="733" xMin="109" yMax="687" yMin="-207"/><wx w="712" xMax="672" xMin="80" yMax="687" yMin="-207"/><wx w="583" xMax="562" xMin="61" yMax="387" yMin="277"/><wx w="548" xMax="611" xMin="60" yMax="791" yMin="-12"/><wx w="712" xMax="682" xMin="39" yMax="470" yMin="105"/><wx w="979" xMax="796" xMin="199" yMax="597" yMin="0"/><wx w="722" xMax="584" xMin="137" yMax="503" yMin="0"/><wx w="273" xMax="342" xMin="-62" yMax="726" yMin="-207"/><wx w="548" xMax="540" xMin="33" yMax="526" yMin="133"/><wx w="548" xMax="549" xMin="28" yMax="645" yMin="18"/><wx w="583" xMax="534" xMin="48" yMax="539" yMin="119"/><wx w="548" xMax="543" xMin="42" yMax="633" yMin="0"/><wx w="548" xMax="543" xMin="42" yMax="633" yMin="0"/><wx w="604" xMax="526" xMin="76" yMax="562" yMin="0"/><wx w="583" xMax="534" xMin="48" yMax="368" yMin="87"/><wx w="604" xMax="477" xMin="266" yMax="833" yMin="-299"/><wx w="604" xMax="338" xMin="127" yMax="833" yMin="-299"/><wx w="708" xMax="713" xMin="-4" yMax="338" yMin="268"/><wx w="625" xMax="301" xMin="230" yMax="910" yMin="-303"/><wx w="708" xMax="713" xMin="318" yMax="338" yMin="-303"/><wx w="708" xMax="389" xMin="-4" yMax="338" yMin="-303"/><wx w="708" xMax="713" xMin="318" yMax="910" yMin="268"/><wx w="708" xMax="389" xMin="-4" yMax="910" yMin="268"/><wx w="708" xMax="713" xMin="318" yMax="910" yMin="-303"/><wx w="708" xMax="389" xMin="-4" yMax="910" yMin="-303"/><wx w="708" xMax="713" xMin="-4" yMax="338" yMin="-303"/><wx w="708" xMax="713" xMin="-4" yMax="910" yMin="268"/><wx w="708" xMax="713" xMin="-4" yMax="910" yMin="-303"/><wx w="708" xMax="713" xMin="-4" yMax="426" yMin="180"/><wx w="708" xMax="477" xMin="230" yMax="910" yMin="-303"/><wx w="708" xMax="713" xMin="318" yMax="426" yMin="-303"/><wx w="708" xMax="713" xMin="230" yMax="338" yMin="-303"/><wx w="708" xMax="713" xMin="230" yMax="426" yMin="-303"/><wx w="708" xMax="389" xMin="-4" yMax="426" yMin="-303"/><wx w="708" xMax="477" xMin="-4" yMax="338" yMin="-303"/><wx w="708" xMax="477" xMin="-4" yMax="426" yMin="-303"/><wx w="708" xMax="713" xMin="318" yMax="910" yMin="180"/><wx w="708" xMax="713" xMin="230" yMax="910" yMin="268"/><wx w="708" xMax="713" xMin="230" yMax="910" yMin="180"/><wx w="708" xMax="389" xMin="-4" yMax="910" yMin="180"/><wx w="708" xMax="477" xMin="-4" yMax="910" yMin="268"/><wx w="708" xMax="477" xMin="-4" yMax="910" yMin="180"/><wx w="708" xMax="713" xMin="318" yMax="910" yMin="-303"/><wx w="708" xMax="713" xMin="230" yMax="910" yMin="-303"/><wx w="708" xMax="713" xMin="230" yMax="910" yMin="-303"/><wx w="708" xMax="389" xMin="-4" yMax="910" yMin="-303"/><wx w="708" xMax="477" xMin="-4" yMax="910" yMin="-303"/><wx w="708" xMax="477" xMin="-4" yMax="910" yMin="-303"/><wx w="708" xMax="713" xMin="-4" yMax="426" yMin="-303"/><wx w="708" xMax="713" xMin="-4" yMax="338" yMin="-303"/><wx w="708" xMax="713" xMin="-4" yMax="426" yMin="-303"/><wx w="708" xMax="713" xMin="-4" yMax="910" yMin="180"/><wx w="708" xMax="713" xMin="-4" yMax="910" yMin="268"/><wx w="708" xMax="713" xMin="-4" yMax="910" yMin="180"/><wx w="708" xMax="713" xMin="-4" yMax="910" yMin="-303"/><wx w="708" xMax="713" xMin="-4" yMax="910" yMin="-303"/><wx w="708" xMax="713" xMin="-4" yMax="910" yMin="-303"/><wx w="708" xMax="708" xMin="0" yMax="910" yMin="303"/><wx w="708" xMax="708" xMin="0" yMax="303" yMin="-303"/><wx w="708" xMax="708" xMin="0" yMax="910" yMin="-303"/><wx w="708" xMax="354" xMin="0" yMax="910" yMin="-303"/><wx w="708" xMax="708" xMin="354" yMax="910" yMin="-303"/><wx w="708" xMax="708" xMin="50" yMax="829" yMin="-255"/><wx w="708" xMax="708" xMin="0" yMax="829" yMin="-255"/><wx w="729" xMax="729" xMin="0" yMax="829" yMin="-303"/><wx w="604" xMax="543" xMin="60" yMax="541" yMin="57"/><wx w="604" xMax="601" xMin="2" yMax="598" yMin="0"/><wx w="354" xMax="301" xMin="53" yMax="435" yMin="187"/><wx w="354" xMax="301" xMin="53" yMax="435" yMin="187"/><wx w="1000" xMax="1000" xMin="0" yMax="300" yMin="0"/><wx w="989" xMax="787" xMin="202" yMax="584" yMin="0"/><wx w="989" xMax="793" xMin="195" yMax="583" yMin="-13"/><wx w="989" xMax="787" xMin="202" yMax="571" yMin="-13"/><wx w="989" xMax="793" xMin="195" yMax="583" yMin="-13"/><wx w="494" xMax="513" xMin="20" yMax="706" yMin="0"/><wx w="604" xMax="522" xMin="81" yMax="520" yMin="79"/><wx w="604" xMax="517" xMin="86" yMax="497" yMin="66"/><wx w="604" xMax="583" xMin="20" yMax="563" yMin="0"/><wx w="604" xMax="583" xMin="20" yMax="563" yMin="0"/><wx w="354" xMax="298" xMin="56" yMax="432" yMin="189"/><wx w="1020" xMax="809" xMin="211" yMax="583" yMin="-13"/><wx w="1052" xMax="824" xMin="227" yMax="583" yMin="-13"/><wx w="916" xMax="756" xMin="159" yMax="528" yMin="-68"/><wx w="750" xMax="518" xMin="231" yMax="562" yMin="39"/><wx w="750" xMax="585" xMin="164" yMax="562" yMin="122"/><wx w="531" xMax="502" xMin="28" yMax="601" yMin="0"/><wx w="656" xMax="626" xMin="29" yMax="597" yMin="0"/><wx w="593" xMax="543" xMin="49" yMax="559" yMin="-11"/><wx w="510" xMax="477" xMin="32" yMax="597" yMin="-12"/><wx w="500" xMax="403" xMin="95" yMax="562" yMin="14"/><wx w="750" xMax="616" xMin="132" yMax="566" yMin="-24"/><wx w="750" xMax="616" xMin="132" yMax="565" yMin="-20"/><wx w="610" xMax="627" xMin="36" yMax="724" yMin="0"/><wx w="610" xMax="627" xMin="36" yMax="724" yMin="0"/><wx w="333" xMax="262" xMin="45" yMax="-28" yMin="-207"/><wx w="333" xMax="261" xMin="92" yMax="408" yMin="259"/><wx w="333" xMax="187" xMin="39" yMax="-38" yMin="-222"/><wx w="333" xMax="356" xMin="34" yMax="690" yMin="338"/><wx w="333" xMax="355" xMin="41" yMax="687" yMin="333"/><wx w="333" xMax="377" xMin="82" yMax="687" yMin="338"/><wx w="333" xMax="357" xMin="45" yMax="694" yMin="333"/><wx w="333" xMax="405" xMin="14" yMax="748" yMin="578"/><wx w="222" xMax="193" xMin="42" yMax="687" yMin="494"/><wx w="222" xMax="181" xMin="31" yMax="785" yMin="591"/><wx w="333" xMax="366" xMin="146" yMax="882" yMin="747"/><wx w="333" xMax="400" xMin="135" yMax="882" yMin="747"/><wx w="333" xMax="442" xMin="81" yMax="895" yMin="747"/><wx w="333" xMax="436" xMin="73" yMax="895" yMin="747"/><wx w="333" xMax="427" xMin="88" yMax="854" yMin="747"/><wx w="333" xMax="462" xMin="54" yMax="889" yMin="746"/><wx w="333" xMax="469" xMin="28" yMax="883" yMin="747"/><wx w="333" xMax="423" xMin="76" yMax="890" yMin="742"/></cid-widths></multibyte-extras><kerning kpx1="1027"><pair kern="-100" kpx2="44"/><pair kern="-100" kpx2="46"/></kerning><kerning kpx1="1033"><pair kern="-100" kpx2="8217"/></kerning><kerning kpx1="1034"><pair kern="-100" kpx2="8217"/></kerning><kerning kpx1="1040"><pair kern="-49" kpx2="1057"/><pair kern="-24" kpx2="1089"/><pair kern="-101" kpx2="1058"/><pair kern="-62" kpx2="1059"/><pair kern="-24" kpx2="1091"/><pair kern="-62" kpx2="1060"/><pair kern="-24" kpx2="1092"/><pair kern="-49" kpx2="1063"/><pair kern="-49" kpx2="1069"/><pair kern="12" kpx2="1072"/><pair kern="-24" kpx2="1073"/><pair kern="37" kpx2="1044"/><pair kern="-24" kpx2="1077"/><pair kern="-38" kpx2="1047"/><pair kern="-75" kpx2="8217"/><pair kern="12" kpx2="1051"/><pair kern="-49" kpx2="1054"/><pair kern="-24" kpx2="1086"/><pair kern="-24" kpx2="1055"/></kerning><kerning kpx1="1041"><pair kern="-13" kpx2="1057"/><pair kern="-38" kpx2="1058"/><pair kern="-24" kpx2="1059"/><pair kern="-13" kpx2="1091"/><pair kern="-25" kpx2="1060"/><pair kern="-13" kpx2="1061"/><pair kern="-13" kpx2="1063"/><pair kern="-49" kpx2="1066"/><pair kern="-24" kpx2="1069"/><pair kern="-24" kpx2="1071"/><pair kern="12" kpx2="1103"/><pair kern="-38" kpx2="1040"/><pair kern="12" kpx2="1044"/><pair kern="-13" kpx2="1046"/><pair kern="-13" kpx2="1047"/><pair kern="12" kpx2="1051"/><pair kern="12" kpx2="1083"/><pair kern="-13" kpx2="1054"/></kerning><kerning kpx1="1042"><pair kern="-24" kpx2="1057"/><pair kern="-62" kpx2="1058"/><pair kern="-62" kpx2="1059"/><pair kern="-13" kpx2="1091"/><pair kern="-38" kpx2="1060"/><pair kern="-38" kpx2="1061"/><pair kern="-13" kpx2="1093"/><pair kern="-38" kpx2="1095"/><pair kern="-62" kpx2="1066"/><pair kern="-24" kpx2="1071"/><pair kern="-38" kpx2="1040"/><pair kern="-24" kpx2="1046"/><pair kern="-24" kpx2="1047"/><pair kern="-24" kpx2="1054"/></kerning><kerning kpx1="1043"><pair kern="-24" kpx2="1088"/><pair kern="-24" kpx2="1091"/><pair kern="-24" kpx2="1099"/><pair kern="-62" kpx2="44"/><pair kern="-24" kpx2="1100"/><pair kern="-62" kpx2="46"/><pair kern="-24" kpx2="1102"/><pair kern="-13" kpx2="1071"/><pair kern="-24" kpx2="1103"/><pair kern="-50" kpx2="1040"/><pair kern="-13" kpx2="1072"/><pair kern="-50" kpx2="1074"/><pair kern="-24" kpx2="1044"/><pair kern="-13" kpx2="1076"/><pair kern="-49" kpx2="1077"/><pair kern="-13" kpx2="1047"/><pair kern="-38" kpx2="1080"/><pair kern="-13" kpx2="1051"/><pair kern="-38" kpx2="1083"/><pair kern="-24" kpx2="1084"/><pair kern="-24" kpx2="1085"/><pair kern="-13" kpx2="1054"/><pair kern="-49" kpx2="1086"/></kerning><kerning kpx1="1044"><pair kern="24" kpx2="1091"/><pair kern="-13" kpx2="1060"/><pair kern="24" kpx2="1063"/><pair kern="12" kpx2="1079"/></kerning><kerning kpx1="1045"><pair kern="12" kpx2="1089"/><pair kern="-13" kpx2="1047"/><pair kern="12" kpx2="1051"/></kerning><kerning kpx1="1046"><pair kern="12" kpx2="1072"/><pair kern="-13" kpx2="1057"/><pair kern="-13" kpx2="1091"/><pair kern="-13" kpx2="1077"/><pair kern="-13" kpx2="1047"/><pair kern="37" kpx2="1063"/><pair kern="12" kpx2="1066"/><pair kern="-13" kpx2="1054"/><pair kern="-13" kpx2="1086"/></kerning><kerning kpx1="1047"><pair kern="-24" kpx2="1057"/><pair kern="-38" kpx2="1058"/><pair kern="-38" kpx2="1059"/><pair kern="-24" kpx2="1060"/><pair kern="-13" kpx2="1076"/><pair kern="-24" kpx2="1046"/><pair kern="24" kpx2="1063"/><pair kern="12" kpx2="1083"/><pair kern="-24" kpx2="1054"/><pair kern="-24" kpx2="1071"/></kerning><kerning kpx1="8216"><pair kern="-37" kpx2="8216"/></kerning><kerning kpx1="8217"><pair kern="-37" kpx2="160"/><pair kern="-18" kpx2="115"/><pair kern="18" kpx2="116"/><pair kern="-37" kpx2="8217"/></kerning><kerning kpx1="1050"><pair kern="-13" kpx2="1057"/><pair kern="-38" kpx2="1089"/><pair kern="12" kpx2="1058"/><pair kern="-13" kpx2="1091"/><pair kern="-38" kpx2="1060"/><pair kern="-38" kpx2="1077"/><pair kern="49" kpx2="1063"/><pair kern="-24" kpx2="1079"/><pair kern="-24" kpx2="1101"/><pair kern="-13" kpx2="1054"/><pair kern="-38" kpx2="1086"/></kerning><kerning kpx1="1051"><pair kern="12" kpx2="1072"/><pair kern="12" kpx2="1091"/><pair kern="-13" kpx2="1060"/></kerning><kerning kpx1="1052"><pair kern="12" kpx2="1072"/><pair kern="12" kpx2="1091"/><pair kern="37" kpx2="1063"/><pair kern="-13" kpx2="1095"/></kerning><kerning kpx1="1054"><pair kern="-38" kpx2="1040"/><pair kern="-62" kpx2="1059"/><pair kern="-13" kpx2="1044"/><pair kern="-24" kpx2="1061"/><pair kern="-38" kpx2="1046"/><pair kern="24" kpx2="1063"/><pair kern="-13" kpx2="1051"/><pair kern="12" kpx2="1084"/><pair kern="-24" kpx2="1071"/><pair kern="12" kpx2="1103"/></kerning><kerning kpx1="8222"><pair kern="-112" kpx2="1026"/><pair kern="-112" kpx2="1058"/><pair kern="-62" kpx2="1063"/><pair kern="-100" kpx2="1066"/><pair kern="-125" kpx2="1035"/></kerning><kerning kpx1="1056"><pair kern="-38" kpx2="1058"/><pair kern="-38" kpx2="1059"/><pair kern="-38" kpx2="1061"/><pair kern="-125" kpx2="44"/><pair kern="-125" kpx2="46"/><pair kern="-24" kpx2="1071"/><pair kern="-62" kpx2="1040"/><pair kern="-38" kpx2="1044"/><pair kern="-13" kpx2="1076"/><pair kern="-13" kpx2="1077"/><pair kern="-38" kpx2="1046"/><pair kern="-38" kpx2="1047"/><pair kern="-13" kpx2="58"/><pair kern="-24" kpx2="187"/><pair kern="-24" kpx2="1051"/><pair kern="-13" kpx2="894"/><pair kern="-13" kpx2="1086"/></kerning><kerning kpx1="1057"><pair kern="-24" kpx2="1040"/><pair kern="24" kpx2="1072"/><pair kern="-38" kpx2="1058"/><pair kern="-38" kpx2="1059"/><pair kern="-13" kpx2="1061"/><pair kern="12" kpx2="1078"/><pair kern="-24" kpx2="1047"/><pair kern="12" kpx2="1063"/><pair kern="12" kpx2="1079"/><pair kern="-13" kpx2="1095"/><pair kern="-49" kpx2="1066"/><pair kern="-24" kpx2="1069"/></kerning><kerning kpx1="1058"><pair kern="-24" kpx2="1088"/><pair kern="-38" kpx2="1089"/><pair kern="-24" kpx2="1091"/><pair kern="-24" kpx2="1093"/><pair kern="-24" kpx2="1097"/><pair kern="-13" kpx2="1099"/><pair kern="-13" kpx2="1100"/><pair kern="-13" kpx2="1102"/><pair kern="-13" kpx2="1103"/><pair kern="-38" kpx2="1040"/><pair kern="24" kpx2="1046"/><pair kern="12" kpx2="1052"/><pair kern="-13" kpx2="1054"/><pair kern="-13" kpx2="1060"/><pair kern="-38" kpx2="44"/><pair kern="12" kpx2="1069"/><pair kern="-38" kpx2="46"/><pair kern="-38" kpx2="1074"/><pair kern="-38" kpx2="1077"/><pair kern="-38" kpx2="1080"/><pair kern="-24" kpx2="1082"/><pair kern="-24" kpx2="1083"/><pair kern="-24" kpx2="1084"/><pair kern="-38" kpx2="1086"/><pair kern="-13" kpx2="1087"/></kerning><kerning kpx1="1059"><pair kern="-24" kpx2="1088"/><pair kern="-49" kpx2="1089"/><pair kern="-24" kpx2="1093"/><pair kern="-24" kpx2="1094"/><pair kern="-24" kpx2="1096"/><pair kern="-24" kpx2="1097"/><pair kern="-24" kpx2="1102"/><pair kern="-24" kpx2="1103"/><pair kern="-75" kpx2="1040"/><pair kern="-38" kpx2="1044"/><pair kern="-13" kpx2="1047"/><pair kern="-13" kpx2="1051"/><pair kern="-13" kpx2="1054"/><pair kern="-38" kpx2="1060"/><pair kern="-75" kpx2="44"/><pair kern="-13" kpx2="1069"/><pair kern="-75" kpx2="46"/><pair kern="-13" kpx2="1071"/><pair kern="-24" kpx2="1073"/><pair kern="-49" kpx2="1074"/><pair kern="-38" kpx2="1075"/><pair kern="-24" kpx2="1076"/><pair kern="-49" kpx2="1077"/><pair kern="-13" kpx2="1078"/><pair kern="-38" kpx2="1079"/><pair kern="-38" kpx2="1080"/><pair kern="-24" kpx2="1081"/><pair kern="-24" kpx2="58"/><pair kern="-24" kpx2="1082"/><pair kern="-38" kpx2="1083"/><pair kern="-24" kpx2="1084"/><pair kern="-24" kpx2="1085"/><pair kern="-24" kpx2="894"/><pair kern="-62" kpx2="1086"/><pair kern="-24" kpx2="1087"/></kerning><kerning kpx1="1060"><pair kern="-38" kpx2="1040"/><pair kern="-62" kpx2="1058"/><pair kern="-62" kpx2="1059"/><pair kern="-24" kpx2="1044"/><pair kern="24" kpx2="1063"/><pair kern="-24" kpx2="1051"/><pair kern="-13" kpx2="1083"/><pair kern="12" kpx2="1052"/><pair kern="-38" kpx2="1071"/></kerning><kerning kpx1="1061"><pair kern="-13" kpx2="1057"/><pair kern="-13" kpx2="1091"/><pair kern="-24" kpx2="1060"/><pair kern="12" kpx2="1047"/><pair kern="-13" kpx2="1069"/><pair kern="-13" kpx2="1054"/><pair kern="-38" kpx2="1086"/></kerning><kerning kpx1="1062"><pair kern="24" kpx2="1072"/></kerning><kerning kpx1="1065"><pair kern="24" kpx2="1072"/><pair kern="24" kpx2="1091"/></kerning><kerning kpx1="1066"><pair kern="-100" kpx2="8217"/><pair kern="-24" kpx2="1071"/></kerning><kerning kpx1="1068"><pair kern="-24" kpx2="1040"/><pair kern="-38" kpx2="1057"/><pair kern="-100" kpx2="1058"/><pair kern="-24" kpx2="1061"/><pair kern="-24" kpx2="1046"/><pair kern="-24" kpx2="1047"/><pair kern="-38" kpx2="1063"/><pair kern="-87" kpx2="8217"/><pair kern="-13" kpx2="1052"/><pair kern="-38" kpx2="1069"/><pair kern="-38" kpx2="1054"/><pair kern="-38" kpx2="1071"/></kerning><kerning kpx1="1069"><pair kern="-13" kpx2="1044"/><pair kern="-24" kpx2="1061"/><pair kern="-24" kpx2="1046"/><pair kern="-24" kpx2="1047"/><pair kern="-24" kpx2="1051"/><pair kern="-38" kpx2="1071"/></kerning><kerning kpx1="1070"><pair kern="-38" kpx2="1040"/><pair kern="-50" kpx2="1058"/><pair kern="-13" kpx2="1061"/><pair kern="-24" kpx2="1046"/><pair kern="12" kpx2="1063"/></kerning><kerning kpx1="1072"><pair kern="-13" kpx2="1091"/><pair kern="-38" kpx2="1095"/><pair kern="12" kpx2="1083"/><pair kern="-13" kpx2="1101"/></kerning><kerning kpx1="1073"><pair kern="-24" kpx2="1091"/><pair kern="-24" kpx2="1093"/><pair kern="-13" kpx2="1078"/><pair kern="-13" kpx2="1079"/><pair kern="-38" kpx2="1095"/><pair kern="-50" kpx2="1098"/><pair kern="-13" kpx2="1083"/><pair kern="-13" kpx2="1084"/><pair kern="-13" kpx2="1101"/></kerning><kerning kpx1="1074"><pair kern="-24" kpx2="1089"/><pair kern="-13" kpx2="1090"/><pair kern="-38" kpx2="1091"/><pair kern="-24" kpx2="1092"/><pair kern="-49" kpx2="1095"/><pair kern="-62" kpx2="1098"/><pair kern="-13" kpx2="1103"/><pair kern="-13" kpx2="1072"/><pair kern="-24" kpx2="1073"/><pair kern="-24" kpx2="1076"/><pair kern="-24" kpx2="1077"/><pair kern="-13" kpx2="1078"/><pair kern="-13" kpx2="1079"/><pair kern="-24" kpx2="1084"/><pair kern="-24" kpx2="1086"/></kerning><kerning kpx1="1075"><pair kern="-13" kpx2="1072"/><pair kern="-24" kpx2="1089"/><pair kern="-38" kpx2="1076"/><pair kern="-24" kpx2="1077"/><pair kern="-24" kpx2="1079"/><pair kern="-13" kpx2="44"/><pair kern="-24" kpx2="1084"/><pair kern="-13" kpx2="46"/><pair kern="-24" kpx2="1086"/><pair kern="-13" kpx2="1103"/></kerning><kerning kpx1="1076"><pair kern="-13" kpx2="1079"/></kerning><kerning kpx1="1077"><pair kern="12" kpx2="1072"/><pair kern="12" kpx2="1073"/><pair kern="12" kpx2="1089"/><pair kern="-13" kpx2="1091"/><pair kern="12" kpx2="1076"/><pair kern="12" kpx2="1092"/><pair kern="-13" kpx2="1093"/><pair kern="-13" kpx2="1078"/><pair kern="-24" kpx2="1095"/><pair kern="12" kpx2="1083"/><pair kern="12" kpx2="1086"/></kerning><kerning kpx1="1078"><pair kern="12" kpx2="1072"/><pair kern="12" kpx2="1073"/><pair kern="12" kpx2="1091"/><pair kern="-13" kpx2="1095"/><pair kern="12" kpx2="1098"/></kerning><kerning kpx1="1079"><pair kern="-13" kpx2="1073"/><pair kern="-13" kpx2="1089"/><pair kern="-38" kpx2="1091"/><pair kern="-13" kpx2="1076"/><pair kern="-13" kpx2="1092"/><pair kern="-13" kpx2="1077"/><pair kern="-13" kpx2="1079"/><pair kern="-49" kpx2="1095"/><pair kern="-49" kpx2="1098"/><pair kern="-13" kpx2="1084"/><pair kern="-13" kpx2="1086"/></kerning><kerning kpx1="1082"><pair kern="12" kpx2="1072"/><pair kern="12" kpx2="1073"/><pair kern="12" kpx2="1091"/><pair kern="-13" kpx2="1095"/><pair kern="24" kpx2="1083"/><pair kern="12" kpx2="1101"/></kerning><kerning kpx1="1083"><pair kern="-13" kpx2="1073"/><pair kern="-13" kpx2="1089"/><pair kern="-13" kpx2="1091"/><pair kern="-13" kpx2="1092"/><pair kern="-13" kpx2="1077"/><pair kern="-24" kpx2="1095"/><pair kern="-13" kpx2="1086"/></kerning><kerning kpx1="1084"><pair kern="-13" kpx2="1079"/></kerning><kerning kpx1="1086"><pair kern="12" kpx2="1072"/><pair kern="-24" kpx2="1091"/><pair kern="-24" kpx2="1093"/><pair kern="-13" kpx2="1078"/><pair kern="-49" kpx2="1095"/><pair kern="-13" kpx2="1101"/></kerning><kerning kpx1="1088"><pair kern="-25" kpx2="1091"/><pair kern="-24" kpx2="1093"/><pair kern="-13" kpx2="1078"/><pair kern="-13" kpx2="1079"/><pair kern="-49" kpx2="1095"/><pair kern="-13" kpx2="1083"/><pair kern="-13" kpx2="1084"/><pair kern="-13" kpx2="1101"/></kerning><kerning kpx1="65"><pair kern="-37" kpx2="160"/><pair kern="-74" kpx2="84"/><pair kern="-74" kpx2="86"/><pair kern="-55" kpx2="87"/><pair kern="-74" kpx2="89"/><pair kern="-55" kpx2="8217"/></kerning><kerning kpx1="1089"><pair kern="-13" kpx2="1091"/><pair kern="-13" kpx2="1092"/><pair kern="-13" kpx2="1093"/><pair kern="-13" kpx2="1078"/><pair kern="-13" kpx2="1079"/><pair kern="-38" kpx2="1095"/><pair kern="-24" kpx2="1098"/></kerning><kerning kpx1="1090"><pair kern="-13" kpx2="1089"/><pair kern="-24" kpx2="1091"/><pair kern="-13" kpx2="1076"/><pair kern="-13" kpx2="1077"/><pair kern="-13" kpx2="1078"/><pair kern="-24" kpx2="1079"/><pair kern="-13" kpx2="1083"/><pair kern="-13" kpx2="44"/><pair kern="-13" kpx2="1084"/><pair kern="-24" kpx2="1101"/><pair kern="-13" kpx2="46"/><pair kern="-13" kpx2="1086"/></kerning><kerning kpx1="1091"><pair kern="12" kpx2="1073"/><pair kern="12" kpx2="1093"/><pair kern="12" kpx2="1078"/><pair kern="12" kpx2="1079"/><pair kern="-38" kpx2="44"/><pair kern="-38" kpx2="46"/><pair kern="12" kpx2="1103"/></kerning><kerning kpx1="1092"><pair kern="-24" kpx2="1091"/><pair kern="-38" kpx2="1095"/></kerning><kerning kpx1="1093"><pair kern="-13" kpx2="1072"/><pair kern="-13" kpx2="1073"/><pair kern="-24" kpx2="1089"/><pair kern="-24" kpx2="1092"/><pair kern="-24" kpx2="1077"/><pair kern="-13" kpx2="1079"/><pair kern="-24" kpx2="1095"/><pair kern="-13" kpx2="1101"/><pair kern="-24" kpx2="1086"/></kerning><kerning kpx1="70"><pair kern="-55" kpx2="65"/><pair kern="-110" kpx2="44"/><pair kern="-110" kpx2="46"/></kerning><kerning kpx1="1094"><pair kern="-13" kpx2="1072"/><pair kern="-38" kpx2="1089"/><pair kern="-13" kpx2="1091"/><pair kern="-38" kpx2="1077"/><pair kern="-13" kpx2="1079"/><pair kern="-38" kpx2="1086"/></kerning><kerning kpx1="1097"><pair kern="-24" kpx2="1077"/><pair kern="-24" kpx2="1086"/></kerning><kerning kpx1="76"><pair kern="-18" kpx2="160"/><pair kern="-74" kpx2="84"/><pair kern="-55" kpx2="86"/><pair kern="-55" kpx2="87"/><pair kern="-74" kpx2="89"/><pair kern="-74" kpx2="8217"/></kerning><kerning kpx1="1100"><pair kern="-24" kpx2="1090"/><pair kern="-100" kpx2="1095"/></kerning><kerning kpx1="1101"><pair kern="-13" kpx2="1073"/><pair kern="-13" kpx2="1089"/><pair kern="-13" kpx2="1092"/><pair kern="-13" kpx2="1077"/><pair kern="-24" kpx2="1093"/><pair kern="-13" kpx2="1078"/><pair kern="-13" kpx2="1079"/><pair kern="-24" kpx2="1084"/><pair kern="-13" kpx2="1086"/></kerning><kerning kpx1="1102"><pair kern="-13" kpx2="1089"/><pair kern="-13" kpx2="1090"/><pair kern="-13" kpx2="1092"/><pair kern="-24" kpx2="1093"/><pair kern="-62" kpx2="1095"/><pair kern="-24" kpx2="1101"/><pair kern="-13" kpx2="1073"/><pair kern="-13" kpx2="1076"/><pair kern="-13" kpx2="1077"/><pair kern="-24" kpx2="1078"/><pair kern="-13" kpx2="1083"/><pair kern="-13" kpx2="1084"/><pair kern="-13" kpx2="1086"/></kerning><kerning kpx1="80"><pair kern="-37" kpx2="160"/><pair kern="-74" kpx2="65"/><pair kern="-128" kpx2="44"/><pair kern="-128" kpx2="46"/></kerning><kerning kpx1="82"><pair kern="-18" kpx2="84"/><pair kern="-18" kpx2="87"/><pair kern="-18" kpx2="89"/></kerning><kerning kpx1="84"><pair kern="-74" kpx2="65"/><pair kern="-37" kpx2="97"/><pair kern="-37" kpx2="99"/><pair kern="-37" kpx2="101"/><pair kern="-18" kpx2="105"/><pair kern="-74" kpx2="44"/><pair kern="-55" kpx2="173"/><pair kern="-74" kpx2="46"/><pair kern="-18" kpx2="79"/><pair kern="-37" kpx2="111"/><pair kern="-18" kpx2="114"/><pair kern="-37" kpx2="115"/><pair kern="-18" kpx2="117"/><pair kern="-37" kpx2="119"/><pair kern="-37" kpx2="121"/><pair kern="-74" kpx2="58"/><pair kern="-74" kpx2="894"/></kerning><kerning kpx1="86"><pair kern="-74" kpx2="65"/><pair kern="-37" kpx2="97"/><pair kern="-37" kpx2="101"/><pair kern="-37" kpx2="105"/><pair kern="-91" kpx2="44"/><pair kern="-37" kpx2="173"/><pair kern="-91" kpx2="46"/><pair kern="-37" kpx2="111"/><pair kern="-18" kpx2="114"/><pair kern="-18" kpx2="117"/><pair kern="-18" kpx2="121"/><pair kern="-37" kpx2="58"/><pair kern="-37" kpx2="894"/></kerning><kerning kpx1="87"><pair kern="-55" kpx2="65"/><pair kern="-18" kpx2="97"/><pair kern="-18" kpx2="101"/><pair kern="-8" kpx2="105"/><pair kern="-74" kpx2="44"/><pair kern="-37" kpx2="173"/><pair kern="-74" kpx2="46"/><pair kern="-18" kpx2="111"/><pair kern="-18" kpx2="114"/><pair kern="-18" kpx2="117"/><pair kern="-18" kpx2="121"/><pair kern="-37" kpx2="58"/><pair kern="-37" kpx2="894"/></kerning><kerning kpx1="89"><pair kern="-18" kpx2="160"/><pair kern="-74" kpx2="65"/><pair kern="-37" kpx2="97"/><pair kern="-37" kpx2="101"/><pair kern="-37" kpx2="105"/><pair kern="-91" kpx2="44"/><pair kern="-74" kpx2="173"/><pair kern="-91" kpx2="46"/><pair kern="-37" kpx2="111"/><pair kern="-37" kpx2="112"/><pair kern="-37" kpx2="113"/><pair kern="-37" kpx2="117"/><pair kern="-37" kpx2="118"/><pair kern="-55" kpx2="58"/><pair kern="-55" kpx2="894"/></kerning><kerning kpx1="1118"><pair kern="-13" kpx2="58"/><pair kern="-38" kpx2="44"/><pair kern="-38" kpx2="46"/><pair kern="-13" kpx2="894"/></kerning><kerning kpx1="102"><pair kern="-18" kpx2="102"/><pair kern="18" kpx2="8217"/></kerning><kerning kpx1="114"><pair kern="37" kpx2="8217"/><pair kern="-55" kpx2="44"/><pair kern="-55" kpx2="46"/></kerning><kerning kpx1="118"><pair kern="-55" kpx2="44"/><pair kern="-55" kpx2="46"/></kerning><kerning kpx1="119"><pair kern="-37" kpx2="44"/><pair kern="-37" kpx2="46"/></kerning><kerning kpx1="121"><pair kern="-37" kpx2="44"/><pair kern="-37" kpx2="46"/></kerning><kerning kpx1="902"><pair kern="-37" kpx2="160"/><pair kern="-28" kpx2="947"/><pair kern="-91" kpx2="932"/><pair kern="-123" kpx2="933"/><pair kern="-57" kpx2="934"/><pair kern="-28" kpx2="967"/><pair kern="-57" kpx2="920"/><pair kern="-123" kpx2="939"/><pair kern="-28" kpx2="957"/><pair kern="-57" kpx2="927"/></kerning><kerning kpx1="908"><pair kern="-40" kpx2="933"/><pair kern="-40" kpx2="939"/></kerning><kerning kpx1="910"><pair kern="-37" kpx2="963"/><pair kern="-37" kpx2="966"/><pair kern="63" kpx2="970"/><pair kern="-37" kpx2="940"/><pair kern="-37" kpx2="972"/><pair kern="-37" kpx2="942"/><pair kern="-37" kpx2="943"/><pair kern="129" kpx2="912"/><pair kern="-88" kpx2="913"/><pair kern="-37" kpx2="945"/><pair kern="-65" kpx2="916"/><pair kern="-37" kpx2="948"/><pair kern="-37" kpx2="951"/><pair kern="-37" kpx2="953"/><pair kern="-37" kpx2="954"/><pair kern="-55" kpx2="923"/><pair kern="-37" kpx2="956"/><pair kern="-37" kpx2="959"/></kerning><kerning kpx1="1168"><pair kern="-24" kpx2="44"/><pair kern="-24" kpx2="46"/></kerning><kerning kpx1="913"><pair kern="-37" kpx2="160"/><pair kern="-28" kpx2="947"/><pair kern="-91" kpx2="932"/><pair kern="-123" kpx2="933"/><pair kern="-57" kpx2="934"/><pair kern="-28" kpx2="967"/><pair kern="-57" kpx2="920"/><pair kern="-55" kpx2="8217"/><pair kern="-123" kpx2="939"/><pair kern="-28" kpx2="957"/><pair kern="-57" kpx2="927"/></kerning><kerning kpx1="915"><pair kern="129" kpx2="912"/><pair kern="-86" kpx2="913"/><pair kern="-86" kpx2="916"/><pair kern="-18" kpx2="953"/><pair kern="63" kpx2="970"/><pair kern="-86" kpx2="923"/><pair kern="-109" kpx2="44"/><pair kern="-109" kpx2="46"/></kerning><kerning kpx1="916"><pair kern="-37" kpx2="160"/><pair kern="-91" kpx2="932"/><pair kern="-123" kpx2="933"/><pair kern="-20" kpx2="920"/><pair kern="-123" kpx2="939"/><pair kern="-20" kpx2="927"/></kerning><kerning kpx1="920"><pair kern="-27" kpx2="913"/><pair kern="-40" kpx2="933"/><pair kern="-40" kpx2="939"/></kerning><kerning kpx1="922"><pair kern="-19" kpx2="963"/><pair kern="-71" kpx2="934"/><pair kern="-19" kpx2="966"/><pair kern="-19" kpx2="969"/><pair kern="-19" kpx2="940"/><pair kern="-19" kpx2="972"/><pair kern="-19" kpx2="974"/><pair kern="-19" kpx2="945"/><pair kern="-19" kpx2="948"/><pair kern="-19" kpx2="950"/><pair kern="-71" kpx2="920"/><pair kern="-19" kpx2="952"/><pair kern="-19" kpx2="958"/><pair kern="-71" kpx2="927"/><pair kern="-19" kpx2="959"/></kerning><kerning kpx1="923"><pair kern="-37" kpx2="160"/><pair kern="-91" kpx2="932"/><pair kern="-123" kpx2="933"/><pair kern="-20" kpx2="920"/><pair kern="-123" kpx2="939"/><pair kern="-20" kpx2="927"/></kerning><kerning kpx1="927"><pair kern="-27" kpx2="913"/><pair kern="-40" kpx2="933"/><pair kern="-40" kpx2="939"/></kerning><kerning kpx1="160"><pair kern="-37" kpx2="65"/><pair kern="-37" kpx2="913"/><pair kern="-37" kpx2="916"/><pair kern="-18" kpx2="933"/><pair kern="-37" kpx2="902"/><pair kern="-18" kpx2="89"/><pair kern="-37" kpx2="923"/><pair kern="-18" kpx2="939"/></kerning><kerning kpx1="929"><pair kern="-74" kpx2="913"/><pair kern="-74" kpx2="916"/><pair kern="-74" kpx2="923"/><pair kern="-127" kpx2="44"/><pair kern="-127" kpx2="46"/></kerning><kerning kpx1="931"><pair kern="-23" kpx2="964"/></kerning><kerning kpx1="932"><pair kern="-37" kpx2="963"/><pair kern="-18" kpx2="965"/><pair kern="-37" kpx2="966"/><pair kern="-37" kpx2="967"/><pair kern="-26" kpx2="968"/><pair kern="63" kpx2="970"/><pair kern="-18" kpx2="971"/><pair kern="-37" kpx2="972"/><pair kern="-18" kpx2="973"/><pair kern="137" kpx2="912"/><pair kern="-74" kpx2="913"/><pair kern="-44" kpx2="916"/><pair kern="-18" kpx2="920"/><pair kern="-44" kpx2="923"/><pair kern="-18" kpx2="927"/><pair kern="-18" kpx2="934"/><pair kern="-18" kpx2="937"/><pair kern="-74" kpx2="44"/><pair kern="-37" kpx2="940"/><pair kern="-55" kpx2="173"/><pair kern="-37" kpx2="941"/><pair kern="-74" kpx2="46"/><pair kern="-37" kpx2="945"/><pair kern="-26" kpx2="947"/><pair kern="-37" kpx2="948"/><pair kern="-37" kpx2="949"/><pair kern="-18" kpx2="951"/><pair kern="-18" kpx2="953"/><pair kern="-74" kpx2="58"/><pair kern="-18" kpx2="956"/><pair kern="-37" kpx2="957"/><pair kern="-74" kpx2="894"/><pair kern="-37" kpx2="959"/></kerning><kerning kpx1="933"><pair kern="-37" kpx2="963"/><pair kern="-37" kpx2="966"/><pair kern="63" kpx2="970"/><pair kern="-90" kpx2="44"/><pair kern="-37" kpx2="940"/><pair kern="-37" kpx2="972"/><pair kern="-74" kpx2="173"/><pair kern="-90" kpx2="46"/><pair kern="-37" kpx2="942"/><pair kern="-37" kpx2="943"/><pair kern="129" kpx2="912"/><pair kern="-88" kpx2="913"/><pair kern="-37" kpx2="945"/><pair kern="-20" kpx2="947"/><pair kern="-65" kpx2="916"/><pair kern="-37" kpx2="948"/><pair kern="-37" kpx2="951"/><pair kern="-37" kpx2="953"/><pair kern="-55" kpx2="58"/><pair kern="-37" kpx2="954"/><pair kern="-55" kpx2="923"/><pair kern="-37" kpx2="956"/><pair kern="-55" kpx2="894"/><pair kern="-37" kpx2="959"/></kerning><kerning kpx1="934"><pair kern="-27" kpx2="913"/><pair kern="-54" kpx2="933"/><pair kern="-54" kpx2="939"/></kerning><kerning kpx1="935"><pair kern="-34" kpx2="969"/><pair kern="-34" kpx2="974"/></kerning><kerning kpx1="936"><pair kern="-20" kpx2="945"/><pair kern="-20" kpx2="963"/><pair kern="-27" kpx2="948"/><pair kern="-20" kpx2="966"/><pair kern="-17" kpx2="952"/><pair kern="-20" kpx2="969"/><pair kern="-20" kpx2="940"/><pair kern="-20" kpx2="972"/><pair kern="-20" kpx2="974"/><pair kern="-20" kpx2="959"/></kerning><kerning kpx1="937"><pair kern="-40" kpx2="933"/><pair kern="-40" kpx2="939"/></kerning><kerning kpx1="939"><pair kern="-37" kpx2="963"/><pair kern="-37" kpx2="966"/><pair kern="63" kpx2="970"/><pair kern="-37" kpx2="940"/><pair kern="-37" kpx2="972"/><pair kern="-37" kpx2="942"/><pair kern="-37" kpx2="943"/><pair kern="129" kpx2="912"/><pair kern="-88" kpx2="913"/><pair kern="-37" kpx2="945"/><pair kern="-65" kpx2="916"/><pair kern="-37" kpx2="948"/><pair kern="-37" kpx2="951"/><pair kern="-37" kpx2="953"/><pair kern="-37" kpx2="954"/><pair kern="-55" kpx2="923"/><pair kern="-37" kpx2="956"/><pair kern="-37" kpx2="959"/></kerning><kerning kpx1="948"><pair kern="-17" kpx2="960"/><pair kern="-18" kpx2="947"/><pair kern="-27" kpx2="967"/></kerning><kerning kpx1="950"><pair kern="-27" kpx2="960"/><pair kern="-107" kpx2="963"/><pair kern="-27" kpx2="964"/><pair kern="-107" kpx2="966"/><pair kern="-107" kpx2="969"/><pair kern="-107" kpx2="940"/><pair kern="-107" kpx2="972"/><pair kern="-38" kpx2="942"/><pair kern="-107" kpx2="974"/><pair kern="-107" kpx2="945"/><pair kern="-27" kpx2="947"/><pair kern="-36" kpx2="948"/><pair kern="-38" kpx2="951"/><pair kern="-20" kpx2="952"/><pair kern="-38" kpx2="953"/><pair kern="-38" kpx2="954"/><pair kern="-27" kpx2="957"/><pair kern="-107" kpx2="959"/></kerning><kerning kpx1="954"><pair kern="-38" kpx2="962"/><pair kern="-38" kpx2="963"/><pair kern="-38" kpx2="966"/><pair kern="-38" kpx2="969"/><pair kern="-38" kpx2="940"/><pair kern="-38" kpx2="972"/><pair kern="-38" kpx2="974"/><pair kern="-38" kpx2="945"/><pair kern="-38" kpx2="948"/><pair kern="-38" kpx2="950"/><pair kern="-38" kpx2="952"/><pair kern="-38" kpx2="958"/><pair kern="-38" kpx2="959"/></kerning><kerning kpx1="955"><pair kern="-14" kpx2="962"/><pair kern="-14" kpx2="963"/><pair kern="-19" kpx2="965"/><pair kern="-14" kpx2="966"/><pair kern="-14" kpx2="969"/><pair kern="-19" kpx2="971"/><pair kern="-14" kpx2="940"/><pair kern="-14" kpx2="972"/><pair kern="-19" kpx2="973"/><pair kern="-14" kpx2="974"/><pair kern="-19" kpx2="944"/><pair kern="-14" kpx2="945"/><pair kern="-14" kpx2="948"/><pair kern="-14" kpx2="950"/><pair kern="-14" kpx2="958"/><pair kern="-14" kpx2="959"/></kerning><kerning kpx1="958"><pair kern="-20" kpx2="945"/><pair kern="-20" kpx2="962"/><pair kern="-20" kpx2="963"/><pair kern="-20" kpx2="948"/><pair kern="-20" kpx2="950"/><pair kern="-20" kpx2="966"/><pair kern="-20" kpx2="940"/><pair kern="-20" kpx2="972"/><pair kern="-20" kpx2="958"/><pair kern="-20" kpx2="959"/></kerning><kerning kpx1="959"><pair kern="-17" kpx2="960"/><pair kern="-18" kpx2="947"/><pair kern="-17" kpx2="964"/><pair kern="-27" kpx2="967"/></kerning><kerning kpx1="960"><pair kern="14" kpx2="966"/><pair kern="14" kpx2="969"/><pair kern="14" kpx2="974"/></kerning><kerning kpx1="961"><pair kern="-17" kpx2="960"/><pair kern="-27" kpx2="967"/></kerning><kerning kpx1="964"><pair kern="14" kpx2="966"/><pair kern="14" kpx2="969"/><pair kern="14" kpx2="974"/></kerning><kerning kpx1="966"><pair kern="-17" kpx2="960"/><pair kern="-18" kpx2="947"/><pair kern="-27" kpx2="967"/><pair kern="-27" kpx2="955"/></kerning><kerning kpx1="967"><pair kern="-14" kpx2="945"/><pair kern="-14" kpx2="962"/><pair kern="-14" kpx2="963"/><pair kern="-14" kpx2="948"/><pair kern="-14" kpx2="950"/><pair kern="-14" kpx2="966"/><pair kern="-14" kpx2="969"/><pair kern="-14" kpx2="940"/><pair kern="-14" kpx2="972"/><pair kern="-14" kpx2="974"/><pair kern="-14" kpx2="959"/></kerning><kerning kpx1="969"><pair kern="-17" kpx2="960"/><pair kern="-18" kpx2="947"/><pair kern="-27" kpx2="967"/></kerning><kerning kpx1="972"><pair kern="-17" kpx2="960"/><pair kern="-18" kpx2="947"/><pair kern="-27" kpx2="967"/></kerning><kerning kpx1="974"><pair kern="-17" kpx2="960"/><pair kern="-18" kpx2="947"/><pair kern="-27" kpx2="967"/></kerning></font-metrics>